pydirectinput/__init__.py
PyDirectInput-1.0.4.dist-info/LICENSE.txt
PyDirectInput-1.0.4.dist-info/METADATA
PyDirectInput-1.0.4.dist-info/WHEEL
PyDirectInput-1.0.4.dist-info/top_level.txt
PyDirectInput-1.0.4.dist-info/RECORD
