Metadata-Version: 2.1
Name: PyDirectInput
Version: 1.0.4
Summary: Python mouse and keyboard input automation for Windows using Direct Input.
Home-page: https://github.com/learncodebygaming/pydirectinput
Author: Ben Johnson
Author-email: ben@learncodebygaming.com
License: UNKNOWN
Platform: UNKNOWN
Classifier: Programming Language :: Python :: 3
Classifier: Intended Audience :: Developers
Classifier: License :: OSI Approved :: MIT License
Classifier: Operating System :: Microsoft :: Windows
Requires-Python: >=3.4
